data_prep_engine/__init__.py
data_prep_engine/autoprep.py
data_prep_engine/core/__init__.py
data_prep_engine/core/standard_table.py
data_prep_engine/diagnostics/__init__.py
data_prep_engine/diagnostics/report.py
data_prep_engine/ingestion/__init__.py
data_prep_engine/ingestion/datasource.py
data_prep_engine/ingestion/loader.py
data_prep_engine/ingestion/adapters/__init__.py
data_prep_engine/ingestion/adapters/base.py
data_prep_engine/ingestion/adapters/csv_adapter.py
data_prep_engine/ingestion/adapters/image_adapter.py
data_prep_engine/ingestion/adapters/json_adapter.py
data_prep_engine/ingestion/adapters/parquet_adapter.py
data_prep_engine/sanitization/__init__.py
data_prep_engine/sanitization/pipeline.py
data_prep_engine/sanitization/steps/__init__.py
data_prep_engine/sanitization/steps/duplicate_handler.py
data_prep_engine/sanitization/steps/missing_handler.py
data_prep_engine/sanitization/steps/outlier_handler.py
data_prep_engine/visualization/artist.py
data_prep_engine-0.1.0.dist-info/licenses/LICENSE
data_prep_engine-0.1.0.dist-info/METADATA
data_prep_engine-0.1.0.dist-info/WHEEL
data_prep_engine-0.1.0.dist-info/top_level.txt
data_prep_engine-0.1.0.dist-info/RECORD
