Metadata-Version: 2.4
Name: data-prep-engine
Version: 0.1.0
Summary: A unified data ingestion and sanitization engine for ML workflows.
Author-email: Venkata Shashank Kowtharapu <venkatashashank.kowtharapu@outlook.com>
Project-URL: Homepage, https://github.com/Shashank-KVS/data-prep-engine.git
Project-URL: Documentation, https://github.com/yourname/data-prep-engine
Project-URL: Source, https://github.com/yourname/data-prep-engine
Project-URL: Issues, https://github.com/yourname/data-prep-engine/issues
Keywords: data-ingestion,data-cleaning,data-preprocessing,machine-learning,sanitization,eda,etl
Classifier: Development Status :: 3 - Alpha
Classifier: Intended Audience :: Developers
Classifier: Programming Language :: Python :: 3
Classifier: License :: OSI Approved :: MIT License
Classifier: Topic :: Scientific/Engineering :: Information Analysis
Requires-Python: >=3.9
License-File: LICENSE
Requires-Dist: pandas>=2.0
Requires-Dist: pyarrow>=16.0
Requires-Dist: numpy>=1.24
Requires-Dist: pillow>=10.0
Requires-Dist: polars>=1.0.0
Requires-Dist: matplotlib>=3.7.0
Dynamic: license-file
